Metadata-Version: 2.1
Name: detection-utils
Version: 1.0.0
Summary: Common functionality for object detection
Home-page: https://github.com/davidmascharka/detection-utils
Author: David Mascharka, Ryan Soklaski, Arjun Majumdar
Author-email: davidmascharka@gmail.com, rsoklaski@gmail.com, arjun.majum@gmail.com
License: MIT
Platform: UNKNOWN
Requires-Python: >=3.6
Provides-Extra: pytorch
